{
    "Description" : {
        "Id" : "guiTxrPort_jkGarrisoned_utr",
        "Name" : "guiTxrPort_jkGarrisoned_utr",
        "Details" : "Random",
        "Icon" : "guiTxrPort_jkGarrisoned_utr"
    },
    "ID" : "guiTxrPort_jkGarrisoned_utr",
    "backgroundColor" : {
        "r" : 0,
        "g" : 0,
        "b" : 0,
        "a" : 0
    },
    "headMesh" : 0.5,
    "hairMesh" : 7,
    "beardMesh" : 0,
    "suitMesh" : 2,
    "scar" : 6,
    "lightRig" : 2,
    "cameraPosition" : 3,
    "complexionTex" : 4,
    "eyebrowTex" : 3,
    "tattooTex" : 3,
    "actualTattooTex" : 5,
    "weights" : [
        54.54961,
        20.39753,
        0.2944972,
        1.202321,
        22.87998,
        0.6760679
    ],
    "browOffsetY" : -0.001303497,
    "browOffsetZ" : -0.005433294,
    "noseBridgeScale" : 0.161144,
    "noseTipScale" : 0.2951479,
    "chinScale" : 0.1607711,
    "cheekOffsetY" : 0.002836896,
    "eyeWidth" : 0.04723189,
    "jawWidth" : 0.06777134,
    "animation" : 2,
    "isCommander" : true,
    "skinToneId" : "Skin_04",
    "eyeColorId" : "Eye_02",
    "hairRootId" : "Hair_09",
    "hairTipId" : "Hair_09",
    "tattooColorId" : "Tattoo_05",
    "lipColorId" : "Lip_01",
    "customPortraitSaveVersion" : 0
}
