{
    "Description" : {
        "Id" : "Yangs_Evil_Twin",
        "Name" : "Yangs_Evil_Twin",
        "Details" : "Random",
        "Icon" : "Yangs_Evil_Twin"
    },
    "ID" : "Yangs_Evil_Twin",
    "backgroundColor" : {
        "r" : 0,
        "g" : 0,
        "b" : 0,
        "a" : 0
    },
    "headMesh" : 0.5,
    "hairMesh" : 15,
    "beardMesh" : 0,
    "suitMesh" : 1,
    "scar" : 6,
    "lightRig" : 0,
    "cameraPosition" : 2,
    "complexionTex" : 2,
    "eyebrowTex" : 2,
    "tattooTex" : 8,
    "actualTattooTex" : 0,
    "weights" : [
        43.94113,
        24.92265,
        1.719382,
        28.77069,
        0.6153508,
        0.03080372
    ],
    "browOffsetY" : -0.0004675266,
    "browOffsetZ" : -0.003253066,
    "noseBridgeScale" : -0.1027152,
    "noseTipScale" : -0.08964369,
    "chinScale" : 0.115471,
    "cheekOffsetY" : -0.0002159828,
    "eyeWidth" : 0.003136617,
    "jawWidth" : -0.03316947,
    "animation" : 0,
    "isCommander" : true,
    "skinToneId" : "Skin_04",
    "eyeColorId" : "Eye_02",
    "hairRootId" : "Hair_13",
    "hairTipId" : "Hair_13",
    "tattooColorId" : "Tattoo_09",
    "lipColorId" : "Lip_01",
    "customPortraitSaveVersion" : 0
}
