{
    "Description" : {
        "Id" : "nova_cat_pilot",
        "Name" : "nova_cat_pilot",
        "Details" : "Random",
        "Icon" : "nova_cat_pilot"
    },
    "ID" : "nova_cat_pilot",
    "backgroundColor" : {
        "r" : 0,
        "g" : 0,
        "b" : 0,
        "a" : 0
    },
    "headMesh" : 0.5,
    "hairMesh" : 2,
    "beardMesh" : 0,
    "suitMesh" : 0,
    "scar" : 0,
    "lightRig" : 1,
    "cameraPosition" : 1,
    "complexionTex" : 3,
    "eyebrowTex" : 5,
    "tattooTex" : 4,
    "actualTattooTex" : 17,
    "weights" : [
        16.68365,
        53.15689,
        23.68747,
        3.823558,
        0.05472439,
        2.593697
    ],
    "browOffsetY" : -0.0004453982,
    "browOffsetZ" : 0.006034658,
    "noseBridgeScale" : -0.1247919,
    "noseTipScale" : 0.1644559,
    "chinScale" : -0.1384046,
    "cheekOffsetY" : 0.002408482,
    "eyeWidth" : 0.03293684,
    "jawWidth" : 0.07063146,
    "animation" : 4,
    "isCommander" : true,
    "skinToneId" : "Skin_07",
    "eyeColorId" : "Eye_01",
    "hairRootId" : "Hair_17",
    "hairTipId" : "Hair_17",
    "tattooColorId" : "Tattoo_07",
    "lipColorId" : "Lip_01",
    "customPortraitSaveVersion" : 0
}
