{
    "Description" : {
        "Id" : "pilot_at_face_p",
        "Name" : "pilot_at_face_p",
        "Details" : "Random",
        "Icon" : "pilot_at_face_p"
    },
    "ID" : "pilot_at_face_p",
    "backgroundColor" : {
        "r" : 0,
        "g" : 0,
        "b" : 0,
        "a" : 0
    },
    "headMesh" : 0.5,
    "hairMesh" : 6,
    "beardMesh" : 0,
    "suitMesh" : 0,
    "scar" : 11,
    "lightRig" : 5,
    "cameraPosition" : 4,
    "complexionTex" : 4,
    "eyebrowTex" : 4,
    "tattooTex" : 2,
    "actualTattooTex" : 8,
    "weights" : [
        22.9606,
        29.09899,
        33.46456,
        2.03113,
        6.574648,
        5.870059
    ],
    "browOffsetY" : 0.004331763,
    "browOffsetZ" : -0.00029064,
    "noseBridgeScale" : -0.154951,
    "noseTipScale" : -0.234291,
    "chinScale" : 0.09931526,
    "cheekOffsetY" : 0.003702604,
    "eyeWidth" : 0.01726594,
    "jawWidth" : -0.07723834,
    "animation" : 2,
    "isCommander" : true,
    "skinToneId" : "Skin_00",
    "eyeColorId" : "Eye_04",
    "hairRootId" : "Hair_03",
    "hairTipId" : "Hair_03",
    "tattooColorId" : "Tattoo_06",
    "lipColorId" : "Lip_01",
    "customPortraitSaveVersion" : 0
}
