{
    "Description" : {
        "Id" : "pilot_custom_Shepard_portrait",
        "Name" : "pilot_custom_Shepard_portrait",
        "Details" : "Random",
        "Icon" : "pilot_custom_Shepard_portrait"
    },
    "ID" : "pilot_custom_Shepard_portrait",
    "backgroundColor" : {
        "r" : 0,
        "g" : 0,
        "b" : 0,
        "a" : 0
    },
    "headMesh" : 0.5,
    "hairMesh" : 12,
    "beardMesh" : 0,
    "suitMesh" : 2,
    "scar" : 0,
    "lightRig" : 1,
    "cameraPosition" : 0,
    "complexionTex" : 0,
    "eyebrowTex" : 2,
    "tattooTex" : 6,
    "actualTattooTex" : 14,
    "weights" : [
        13.65733,
        27.68618,
        7.000726,
        35.33421,
        6.460401,
        9.861157
    ],
    "browOffsetY" : 0.003378932,
    "browOffsetZ" : 0.005582728,
    "noseBridgeScale" : 0.1206234,
    "noseTipScale" : 0.1434736,
    "chinScale" : 0.08607716,
    "cheekOffsetY" : -0.002727972,
    "eyeWidth" : -0.01453592,
    "jawWidth" : -0.03923992,
    "animation" : 4,
    "isCommander" : true,
    "skinToneId" : "Skin_01",
    "eyeColorId" : "Eye_03",
    "hairRootId" : "Hair_13",
    "hairTipId" : "Hair_13",
    "tattooColorId" : "Tattoo_04",
    "lipColorId" : "Lip_01",
    "customPortraitSaveVersion" : 0
}
