{
    "Description" : {
        "Id" : "tim",
        "Name" : "tim",
        "Details" : "Random",
        "Icon" : "tim"
    },
    "ID" : "tim",
    "backgroundColor" : {
        "r" : 0,
        "g" : 0,
        "b" : 0,
        "a" : 0
    },
    "headMesh" : 0.5,
    "hairMesh" : 4,
    "beardMesh" : 0,
    "suitMesh" : 2,
    "scar" : 0,
    "lightRig" : 4,
    "cameraPosition" : 3,
    "complexionTex" : 2,
    "eyebrowTex" : 1,
    "tattooTex" : 8,
    "actualTattooTex" : 0,
    "weights" : [
        56.61937,
        16.24842,
        23.40861,
        1.803542,
        1.081944,
        0.8381203
    ],
    "browOffsetY" : 0.006289043,
    "browOffsetZ" : 0.00243438,
    "noseBridgeScale" : 0.009278893,
    "noseTipScale" : -0.03804706,
    "chinScale" : 0.05481543,
    "cheekOffsetY" : 0.003180581,
    "eyeWidth" : 0.03580536,
    "jawWidth" : 0.09746242,
    "animation" : 3,
    "isCommander" : true,
    "skinToneId" : "Skin_04",
    "eyeColorId" : "Eye_06",
    "hairRootId" : "Hair_12",
    "hairTipId" : "Hair_12",
    "tattooColorId" : "Tattoo_02",
    "lipColorId" : "Lip_01",
    "customPortraitSaveVersion" : 0
}
